must_gather_parser/__init__.py
must_gather_parser/must_gather.py
must_gather_parser-0.4.2.dist-info/METADATA
must_gather_parser-0.4.2.dist-info/WHEEL
must_gather_parser-0.4.2.dist-info/licenses/LICENSE
must_gather_parser-0.4.2.dist-info/RECORD
