Metadata-Version: 2.4
Name: must-gather-parser
Version: 0.4.2
Summary: Asynchronous (multi) must-gather parsing library.
License-File: LICENSE
Author: Gabriel Meghnagi
Author-email: gabrielmeghnagi@outlook.com
Requires-Python: >=3.11
Classifier: Programming Language :: Python :: 3
Classifier: Programming Language :: Python :: 3.11
Classifier: Programming Language :: Python :: 3.12
Classifier: Programming Language :: Python :: 3.13
Classifier: Programming Language :: Python :: 3.14
Requires-Dist: aiofiles (>=25.1.0,<26.0.0)
Requires-Dist: pyyaml (>=6.0.3,<7.0.0)
